graph_library/__init__.py
graph_library/bfs.py
graph_library/dfs.py
tests/__init__.py
tests/test_bfs.py
tests/test_dfs.py
graph_library_shahriar-1.0.0.dist-info/LICENSE
graph_library_shahriar-1.0.0.dist-info/METADATA
graph_library_shahriar-1.0.0.dist-info/WHEEL
graph_library_shahriar-1.0.0.dist-info/top_level.txt
graph_library_shahriar-1.0.0.dist-info/RECORD
