Metadata-Version: 2.1
Name: graph-library-shahriar
Version: 1.0.0
Summary: A library for BFS and DFS graph traversal algorithms.
Author: Shahriar Ahmed
Author-email: shahriarahmed99bd@gmail.com
Classifier: Programming Language :: Python :: 3
Classifier: License :: OSI Approved :: MIT License
Classifier: Operating System :: OS Independent
Requires-Python: >=3.6
License-File: LICENSE
